scalegen_function_calling/__init__.py
scalegen_function_calling/client.py
scalegen_function_calling/mistral_client.py
scalegen_function_calling/vector_store.py
scalegen_function_calling-0.1.8.dist-info/LICENSE
scalegen_function_calling-0.1.8.dist-info/METADATA
scalegen_function_calling-0.1.8.dist-info/WHEEL
scalegen_function_calling-0.1.8.dist-info/top_level.txt
scalegen_function_calling-0.1.8.dist-info/RECORD
