Metadata-Version: 2.1
Name: scalegen-function-calling
Version: 0.1.8
Summary: A package for generating function calls using OpenAI's API for ScaleGenAI's function calling models
Home-page: https://github.com/ScaleGenAI/function-calling-openai-sdk
Author: Tejesh Bhalla
Author-email: tejeshbhalla1@gmail.com
License: MIT
Classifier: Programming Language :: Python :: 3
Classifier: License :: OSI Approved :: MIT License
Classifier: Operating System :: OS Independent
Requires-Python: >=3.7
License-File: LICENSE
Requires-Dist: openai
Requires-Dist: jinja2
Requires-Dist: mistral-common
Requires-Dist: fastembed
Requires-Dist: qdrant-client[fastembed]
Requires-Dist: nuitka
